LICENSE
MANIFEST.in
README
dum.py
dumxpath.py
setup.py
doc/conf.py
doc/csvtutorial.rst
doc/dumxpath.rst
doc/index.rst
doc/intro.rst
doc/jsontutorial.rst
doc/reference.rst
doc/xmltutorial.rst
dum.egg-info/PKG-INFO
dum.egg-info/SOURCES.txt
dum.egg-info/dependency_links.txt
dum.egg-info/top_level.txt
samples/plist.py
samples/schema.py
tests/__init__.py
tests/testatoms.py
tests/testconvert.py
tests/testcsv.py
tests/testgroup.py
tests/testjson.py
tests/testjspath.py
tests/testlist.py
tests/testnamespace.py
tests/testnode.py
tests/testxml.py