Metadata-Version: 1.0
Name: dum
Version: 0.4
Summary: Direct data to object for xml, jon and csv
Home-page: https://bitbucket.org/sebkeim/dum
Author: Sébastien Keim
Author-email: s.keim@free.fr
License: MIT
Keywords: xml csv json
Platform: UNKNOWN
Classifier: Development Status :: 3 - Alpha
Classifier: Intended Audience :: Developers
Classifier: Topic :: Text Processing :: Markup
Classifier: Topic :: Software Development :: Libraries :: Python Modules
Classifier: License :: OSI Approved :: MIT License
Classifier: Programming Language :: Python :: 3
